Metadata-Version: 1.0
Name: distributions-bino-gauss
Version: 1.0
Summary: Gaussian and Binomial distributions
Home-page: UNKNOWN
Author: Parul
Author-email: parulagarwal.agarwal@gmail.com
License: UNKNOWN
Platform: UNKNOWN
